myRIO_API/__init__.py
myRIO_API/myRIO_API.py
myRIO_API/version.py
myRIO_API/examples/README_server.txt
myRIO_API/examples/myRIO_API
myRIO_API_client/__init__.py
myRIO_API_client/myRIO_API_client.py
myRIO_API_client/version.py
myRIO_API_client/examples/README_client.txt
myRIO_API_client/examples/client_examples.py
myRIO_base/__init__.py
myRIO_base/myRIO_base.py
myRIO_base/version.py
myRIO_base/data/Default.lvbitx
myRIO_base/data/High-throughput.lvbitx
myRIO_base/examples/PWM_tests.py
myRIO_base/examples/PacManDeath.csv
myRIO_base/examples/analog-inputs-and-outputs.py
myRIO_base/examples/digital-inputs-and-outputs.py
myRIO_base/examples/mxp-board-tests.py
myRIO_base/examples/waveform-test.py
myRIO_library-1.3.3.dist-info/METADATA
myRIO_library-1.3.3.dist-info/WHEEL
myRIO_library-1.3.3.dist-info/top_level.txt
myRIO_library-1.3.3.dist-info/RECORD
