Metadata-Version: 2.1
Name: myRIO_library
Version: 1.3.3
Summary: A library to control the myRIO board from National Instruments
Home-page: https://github.com/AitzolEzeizaUPVEHU/myRIO_library
Download-URL: https://github.com/AitzolEzeizaUPVEHU/myRIO_library/archive/refs/heads/main.zip
Author: Aitzol Ezeiza Ramos
Author-email: aitzol.ezeiza@ehu.eus
License: MIT
Keywords: myRIO,NI,National Instruments,LabVIEW,Python,FPGA,Real-Time,Embedded Systems
Classifier: Programming Language :: Python :: 3
Classifier: License :: OSI Approved :: MIT License
Classifier: Operating System :: Other OS
Classifier: Operating System :: OS Independent
Requires-Python: >=3.5
Requires-Dist: nifpga >=22.0.0
Requires-Dist: future >=1.0.0
Requires-Dist: Flask >=1.1.4
Requires-Dist: Jinja2 >=2.11.3
Requires-Dist: Werkzeug >=1.0.1
Requires-Dist: click >=7.1.2
Requires-Dist: itsdangerous >=1.1.0
Requires-Dist: MarkupSafe >=0.23
Requires-Dist: Waitress >=1.4.0
Requires-Dist: requests >=2.25.1
